cdmtb/__about__.py
cdmtb/__init__.py
cdmtb/cdmtb.py
cdmtb-0.2.4.dist-info/METADATA
cdmtb-0.2.4.dist-info/WHEEL
cdmtb-0.2.4.dist-info/licenses/LICENSE.txt
cdmtb-0.2.4.dist-info/RECORD
