Metadata-Version: 2.3
Name: cdmtb
Version: 0.2.4
Summary: Control System Design Toolbox in Python for Coefficient Diagram Method (CDM)
Project-URL: Documentation, https://github.com/hirokawa/cdmtb#readme
Project-URL: Issues, https://github.com/hiirokawa/cdmtb/issues
Project-URL: Source, https://github.com/hiirokawa/cdmtb
Author-email: Rui Hirokawa <rui.hirokawa@gmail.com>
License-Expression: MIT
License-File: LICENSE.txt
Keywords: CDM,Control System Design
Classifier: Development Status :: 4 - Beta
Classifier: Programming Language :: Python
Classifier: Programming Language :: Python :: 3.8
Classifier: Programming Language :: Python :: 3.9
Classifier: Programming Language :: Python :: 3.10
Classifier: Programming Language :: Python :: 3.11
Classifier: Programming Language :: Python :: 3.12
Classifier: Programming Language :: Python :: Implementation :: CPython
Classifier: Programming Language :: Python :: Implementation :: PyPy
Requires-Python: >=3.8
